dpyuserembed/__init__.py
dpyuserembed/utils/__init__.py
dpyuserembed/utils/embed.py
dpyuserembed/utils/shortener.py
dpyuserembed-0.0.5.dist-info/LICENSE
dpyuserembed-0.0.5.dist-info/METADATA
dpyuserembed-0.0.5.dist-info/WHEEL
dpyuserembed-0.0.5.dist-info/top_level.txt
dpyuserembed-0.0.5.dist-info/RECORD
