Metadata-Version: 2.1
Name: dpyuserembed
Version: 0.0.5
Summary: A package to allow discord users to use embeds again
Author-email: Colton Milford <coltonmilford10@gmail.com>
Classifier: Programming Language :: Python :: 3
Classifier: License :: OSI Approved :: MIT License
Classifier: Operating System :: OS Independent
License-File: LICENSE
